PreproX/__init__.py
PreproX/encoding.py
PreproX/exceptions.py
PreproX/imputation.py
PreproX/inspection.py
PreproX/logging.py
PreproX/preprocessing.py
PreproX/scaling.py
PreproX/transformers.py
PreproX/utils.py
PreproX/visualizations.py
PreproX-0.1.6.dist-info/METADATA
PreproX-0.1.6.dist-info/WHEEL
PreproX-0.1.6.dist-info/top_level.txt
PreproX-0.1.6.dist-info/RECORD
